argos3/__init__.py
argos3/bersnr.py
argos3/channel.py
argos3/convolutional.py
argos3/data.py
argos3/datagram.py
argos3/detector.py
argos3/encoder.py
argos3/env_vars.py
argos3/formatter.py
argos3/lowpassfilter.py
argos3/matchedfilter.py
argos3/modulator.py
argos3/multiplexer.py
argos3/noise.py
argos3/plotter.py
argos3/preamble.py
argos3/receiver.py
argos3/sampler.py
argos3/scrambler.py
argos3/synchronizer.py
argos3/transmitter.py
argos3-1.0.7.dist-info/licenses/LICENSE
argos3-1.0.7.dist-info/METADATA
argos3-1.0.7.dist-info/WHEEL
argos3-1.0.7.dist-info/top_level.txt
argos3-1.0.7.dist-info/RECORD
