Metadata-Version: 2.4
Name: argos3
Version: 1.0.7
Summary: An open-source tool for analysis and simulation of ARGOS-3 communication standard
Author-email: Arthur Cadore <arthurbarcella.ifsc@gmail.com>
License-Expression: MIT
Project-URL: Homepage, https://arthurcadore.github.io/argos3/
Project-URL: Repository, https://github.com/arthurcadore/argos3
Requires-Python: >=3.8
License-File: LICENSE
Requires-Dist: numpy>=1.21.0
Requires-Dist: matplotlib>=3.4.0
Requires-Dist: scipy>=1.7.0
Requires-Dist: komm>=0.7.0
Requires-Dist: scienceplots>=2.1.1
Dynamic: license-file
